pyaaisc/__init__.py
pyaaisc/scrape.py
pyaaisc-1.2.dist-info/LICENSE
pyaaisc-1.2.dist-info/METADATA
pyaaisc-1.2.dist-info/WHEEL
pyaaisc-1.2.dist-info/top_level.txt
pyaaisc-1.2.dist-info/RECORD
