Metadata-Version: 2.1
Name: pyaaisc
Version: 1.2
Summary: Python AAindex database scrape
Home-page: https://github.com/stefs304/pyaaisc
Author: Stefan Stojanovic
Author-email: stefs304@gmail.com
License: UNKNOWN
Platform: UNKNOWN
Classifier: Programming Language :: Python :: 3.7
Classifier: Programming Language :: Python :: 3.6
Classifier: License :: OSI Approved :: MIT License
Classifier: Intended Audience :: Science/Research
Classifier: Topic :: Scientific/Engineering :: Bio-Informatics
Classifier: Topic :: Scientific/Engineering :: Chemistry
Requires-Dist: beautifulsoup4
Requires-Dist: requests
